listmod/__init__.py
listmod/main.py
listmodpkg-0.0.1.dist-info/METADATA
listmodpkg-0.0.1.dist-info/WHEEL
listmodpkg-0.0.1.dist-info/top_level.txt
listmodpkg-0.0.1.dist-info/RECORD
